donna25519/__init__.py
donna25519/_curve25519.pyd
donna25519/keys.py
donna25519-0.1.1.dist-info/DESCRIPTION.rst
donna25519-0.1.1.dist-info/METADATA
donna25519-0.1.1.dist-info/RECORD
donna25519-0.1.1.dist-info/WHEEL
donna25519-0.1.1.dist-info/metadata.json
donna25519-0.1.1.dist-info/top_level.txt
