Metadata-Version: 2.0
Name: donna25519
Version: 0.1.1
Summary: Python wrapper for the Curve25519-donna cryptographic library
Home-page: https://github.com/Muterra/donna25519
Author: Nick Badger
Author-email: badg@muterra.io
License: BSD
Keywords: curve25519,curve 25519,donna,cryptography,ecdh,ecdhe,elliptic curve cryptography,ecc,diffie hellman,key agreement
Platform: UNKNOWN
Classifier: Development Status :: 4 - Beta
Classifier: Intended Audience :: Developers
Classifier: Topic :: Security :: Cryptography
Classifier: Topic :: Software Development
Classifier: Topic :: Utilities
Classifier: License :: OSI Approved :: BSD License
Classifier: Programming Language :: Python :: 3
Classifier: Programming Language :: Python :: 3.3
Classifier: Programming Language :: Python :: 3.4
Classifier: Programming Language :: Python :: 3.5
